pages/__init__.py
pages/dataloaders.py
pages/scripts.py
pages/templateplugins.py
pages/templating.py
pages-0.3.dist-info/LICENSE.txt
pages-0.3.dist-info/METADATA
pages-0.3.dist-info/WHEEL
pages-0.3.dist-info/entry_points.txt
pages-0.3.dist-info/top_level.txt
pages-0.3.dist-info/RECORD
