Metadata-Version: 2.1
Name: pages
Version: 0.3
Summary: Static site generator
Home-page: https://sr.ht/~olly/pages
Author: Oliver Cope
Author-email: oliver@redgecko.org
License: Apache
Platform: UNKNOWN
Provides-Extra: markdown
Provides-Extra: jinja2
Provides-Extra: chameleon
Provides-Extra: kajiki
Provides-Extra: genshi
License-File: LICENSE.txt
